{
	"718682": [
		[
			"W",
			747340,
			3532657
		],
		[
			"L",
			725503,
			3533933
		],
		null
	],
	"725503": [
		[
			"W",
			755359,
			3531241
		],
		[
			"W",
			718682,
			3533933
		],
		[
			"L",
			753318,
			3536106
		]
	],
	"731271": [
		[
			"L",
			760932,
			3531683
		],
		null,
		null
	],
	"747340": [
		[
			"L",
			718682,
			3532657
		],
		null,
		null
	],
	"753318": [
		[
			"W",
			758818,
			3531582
		],
		[
			"W",
			760932,
			3535343
		],
		[
			"W",
			725503,
			3536106
		]
	],
	"755359": [
		[
			"L",
			725503,
			3531241
		],
		null,
		null
	],
	"758818": [
		[
			"L",
			753318,
			3531582
		],
		null,
		null
	],
	"760932": [
		[
			"W",
			731271,
			3531683
		],
		[
			"L",
			753318,
			3535343
		],
		null
	]
}