{
	"137306": [
		[
			"b",
			null,
			null
		],
		[
			"F",
			404891,
			null
		],
		null,
		null,
		null
	],
	"292341": [
		[
			"W",
			749263,
			3508812
		],
		[
			"W",
			721044,
			3510643
		],
		[
			"L",
			482739,
			3513170
		],
		null,
		null
	],
	"297146": [
		[
			"b",
			null,
			null
		],
		[
			"L",
			572140,
			3509098
		],
		null,
		null,
		null
	],
	"403922": [
		[
			"W",
			686860,
			3510341
		],
		[
			"L",
			482739,
			3512495
		],
		null,
		null,
		null
	],
	"404891": [
		[
			"W",
			750920,
			3509384
		],
		[
			"B",
			137306,
			null
		],
		[
			"L",
			720903,
			3516534
		],
		null,
		null
	],
	"482739": [
		[
			"W",
			501086,
			3508575
		],
		[
			"W",
			403922,
			3512495
		],
		[
			"W",
			292341,
			3513170
		],
		[
			"L",
			720903,
			3520142
		],
		null
	],
	"501086": [
		[
			"L",
			482739,
			3508575
		],
		null,
		null,
		null,
		null
	],
	"572140": [
		[
			"b",
			null,
			null
		],
		[
			"W",
			297146,
			3509098
		],
		[
			"L",
			655474,
			3512063
		],
		null,
		null
	],
	"649122": [
		[
			"b",
			null,
			null
		],
		[
			"W",
			733215,
			3508802
		],
		[
			"W",
			740751,
			3510171
		],
		[
			"L",
			655474,
			3513722
		],
		null
	],
	"655474": [
		[
			"b",
			null,
			null
		],
		[
			"W",
			668852,
			3508821
		],
		[
			"W",
			572140,
			3512063
		],
		[
			"W",
			649122,
			3513722
		],
		[
			"L",
			720903,
			3523792
		]
	],
	"657172": [
		[
			"b",
			null,
			null
		],
		[
			"L",
			740751,
			3510046
		],
		null,
		null,
		null
	],
	"663140": [
		[
			"L",
			720903,
			3509862
		],
		null,
		null,
		null,
		null
	],
	"668852": [
		[
			"b",
			null,
			null
		],
		[
			"L",
			655474,
			3508821
		],
		null,
		null,
		null
	],
	"686860": [
		[
			"L",
			403922,
			3510341
		],
		null,
		null,
		null,
		null
	],
	"702805": [
		[
			"W",
			753610,
			3509495
		],
		[
			"L",
			720903,
			3510247
		],
		null,
		null,
		null
	],
	"720903": [
		[
			"W",
			663140,
			3509862
		],
		[
			"W",
			702805,
			3510247
		],
		[
			"W",
			404891,
			3516534
		],
		[
			"W",
			482739,
			3520142
		],
		[
			"W",
			655474,
			3523792
		]
	],
	"721044": [
		[
			"W",
			735851,
			3510158
		],
		[
			"L",
			292341,
			3510643
		],
		null,
		null,
		null
	],
	"733215": [
		[
			"b",
			null,
			null
		],
		[
			"L",
			649122,
			3508802
		],
		null,
		null,
		null
	],
	"735851": [
		[
			"L",
			721044,
			3510158
		],
		null,
		null,
		null,
		null
	],
	"740751": [
		[
			"b",
			null,
			null
		],
		[
			"W",
			657172,
			3510046
		],
		[
			"L",
			649122,
			3510171
		],
		null,
		null
	],
	"749263": [
		[
			"L",
			292341,
			3508812
		],
		null,
		null,
		null,
		null
	],
	"750920": [
		[
			"L",
			404891,
			3509384
		],
		null,
		null,
		null,
		null
	],
	"753610": [
		[
			"L",
			702805,
			3509495
		],
		null,
		null,
		null,
		null
	]
}