{
	"113558": [
		[
			"W",
			324410,
			1581830
		],
		[
			"W",
			231298,
			1581917
		],
		[
			"L",
			301307,
			1593753
		]
	],
	"231298": [
		[
			"W",
			305157,
			1581824
		],
		[
			"L",
			113558,
			1581917
		],
		null
	],
	"257871": [
		[
			"L",
			301307,
			1581816
		],
		null,
		null
	],
	"301307": [
		[
			"W",
			257871,
			1581816
		],
		[
			"W",
			305046,
			1581956
		],
		[
			"W",
			113558,
			1593753
		]
	],
	"305046": [
		[
			"W",
			332082,
			1581822
		],
		[
			"L",
			301307,
			1581956
		],
		null
	],
	"305157": [
		[
			"L",
			231298,
			1581824
		],
		null,
		null
	],
	"324410": [
		[
			"L",
			113558,
			1581830
		],
		null,
		null
	],
	"332082": [
		[
			"L",
			305046,
			1581822
		],
		null,
		null
	]
}