{
	"109665": [
		[
			"W",
			243168,
			1497358
		],
		[
			"L",
			152823,
			1497488
		],
		null
	],
	"152823": [
		[
			"W",
			308099,
			1497356
		],
		[
			"W",
			109665,
			1497488
		],
		[
			"W",
			302063,
			1498801
		]
	],
	"243168": [
		[
			"L",
			109665,
			1497358
		],
		null,
		null
	],
	"280316": [
		[
			"W",
			300279,
			1497307
		],
		[
			"L",
			302063,
			1497462
		],
		null
	],
	"300279": [
		[
			"L",
			280316,
			1497307
		],
		null,
		null
	],
	"302063": [
		[
			"W",
			319155,
			1497366
		],
		[
			"W",
			280316,
			1497462
		],
		[
			"L",
			152823,
			1498801
		]
	],
	"308099": [
		[
			"L",
			152823,
			1497356
		],
		null,
		null
	],
	"319155": [
		[
			"L",
			302063,
			1497366
		],
		null,
		null
	]
}