{
	"298602": [
		[
			"F",
			675204,
			null
		],
		null,
		null,
		null
	],
	"305132": [
		[
			"L",
			655859,
			3245730
		],
		null,
		null,
		null
	],
	"310532": [
		[
			"L",
			354384,
			3245632
		],
		null,
		null,
		null
	],
	"341712": [
		[
			"L",
			566647,
			3246103
		],
		null,
		null,
		null
	],
	"345292": [
		[
			"B",
			679171,
			null
		],
		[
			"W",
			675204,
			3248434
		],
		[
			"L",
			354384,
			3251190
		],
		null
	],
	"354384": [
		[
			"W",
			310532,
			3245632
		],
		[
			"W",
			616691,
			3246876
		],
		[
			"W",
			345292,
			3251190
		],
		[
			"L",
			510150,
			3254034
		]
	],
	"510150": [
		[
			"W",
			655514,
			3245041
		],
		[
			"W",
			655859,
			3247879
		],
		[
			"W",
			566647,
			3252743
		],
		[
			"W",
			354384,
			3254034
		]
	],
	"566647": [
		[
			"W",
			341712,
			3246103
		],
		[
			"W",
			678542,
			3249349
		],
		[
			"L",
			510150,
			3252743
		],
		null
	],
	"616691": [
		[
			"b",
			null,
			null
		],
		[
			"C",
			354384,
			3246876
		],
		null,
		null
	],
	"655514": [
		[
			"L",
			510150,
			3245041
		],
		null,
		null,
		null
	],
	"655859": [
		[
			"W",
			305132,
			3245730
		],
		[
			"L",
			510150,
			3247879
		],
		null,
		null
	],
	"667234": [
		[
			"L",
			678542,
			3246709
		],
		null,
		null,
		null
	],
	"675204": [
		[
			"B",
			298602,
			null
		],
		[
			"L",
			345292,
			3248434
		],
		null,
		null
	],
	"678542": [
		[
			"W",
			667234,
			3246709
		],
		[
			"L",
			566647,
			3249349
		],
		null,
		null
	],
	"679171": [
		[
			"F",
			345292,
			null
		],
		null,
		null,
		null
	]
}