{
	"41226": [
		[
			"W",
			207897,
			1015410
		],
		[
			"W",
			207502,
			1015492
		],
		[
			"L",
			140749,
			1015629
		]
	],
	"98227": [
		[
			"L",
			114795,
			1015380
		],
		null,
		null
	],
	"114795": [
		[
			"W",
			98227,
			1015380
		],
		[
			"L",
			140749,
			1015476
		],
		null
	],
	"140749": [
		[
			"W",
			204976,
			1015390
		],
		[
			"W",
			114795,
			1015476
		],
		[
			"W",
			41226,
			1015629
		]
	],
	"163563": [
		[
			"L",
			207502,
			1015354
		],
		null,
		null
	],
	"204976": [
		[
			"L",
			140749,
			1015390
		],
		null,
		null
	],
	"207502": [
		[
			"W",
			163563,
			1015354
		],
		[
			"L",
			41226,
			1015492
		],
		null
	],
	"207897": [
		[
			"L",
			41226,
			1015410
		],
		null,
		null
	]
}