{
	"209930": [
		[
			"W",
			211604,
			975989
		],
		[
			"L",
			210542,
			977120
		],
		null,
		null
	],
	"210074": [
		[
			"W",
			212054,
			963240
		],
		[
			"W",
			211591,
			987588
		],
		[
			"L",
			211740,
			1001150
		],
		null
	],
	"210542": [
		[
			"W",
			211935,
			976741
		],
		[
			"W",
			209930,
			977120
		],
		[
			"L",
			210613,
			994725
		],
		null
	],
	"210613": [
		[
			"W",
			211605,
			981261
		],
		[
			"W",
			211750,
			991241
		],
		[
			"W",
			210542,
			994725
		],
		[
			"W",
			211740,
			1016431
		]
	],
	"210958": [
		[
			"L",
			211750,
			968664
		],
		null,
		null,
		null
	],
	"211016": [
		[
			"L",
			211591,
			977216
		],
		null,
		null,
		null
	],
	"211246": [
		[
			"L",
			211599,
			977184
		],
		null,
		null,
		null
	],
	"211591": [
		[
			"W",
			211016,
			977216
		],
		[
			"L",
			210074,
			987588
		],
		null,
		null
	],
	"211599": [
		[
			"W",
			211246,
			977184
		],
		[
			"L",
			211740,
			999138
		],
		null,
		null
	],
	"211604": [
		[
			"C",
			209930,
			975989
		],
		null,
		null,
		null
	],
	"211605": [
		[
			"L",
			210613,
			981261
		],
		null,
		null,
		null
	],
	"211740": [
		[
			"W",
			211918,
			977306
		],
		[
			"W",
			211599,
			999138
		],
		[
			"W",
			210074,
			1001150
		],
		[
			"L",
			210613,
			1016431
		]
	],
	"211750": [
		[
			"W",
			210958,
			968664
		],
		[
			"L",
			210613,
			991241
		],
		null,
		null
	],
	"211918": [
		[
			"L",
			211740,
			977306
		],
		null,
		null,
		null
	],
	"211935": [
		[
			"L",
			210542,
			976741
		],
		null,
		null,
		null
	],
	"212054": [
		[
			"L",
			210074,
			963240
		],
		null,
		null,
		null
	]
}