{
	"766759": [
		[
			"W",
			816384,
			3995091
		],
		[
			"W",
			899425,
			3996891
		],
		[
			"L",
			894265,
			3997716
		]
	],
	"816384": [
		[
			"L",
			766759,
			3995091
		],
		null,
		null
	],
	"878593": [
		[
			"L",
			894265,
			3995114
		],
		null,
		null
	],
	"894265": [
		[
			"W",
			878593,
			3995114
		],
		[
			"W",
			895172,
			3997433
		],
		[
			"W",
			766759,
			3997716
		]
	],
	"895172": [
		[
			"W",
			902409,
			3994754
		],
		[
			"L",
			894265,
			3997433
		],
		null
	],
	"897502": [
		[
			"L",
			899425,
			3995836
		],
		null,
		null
	],
	"899425": [
		[
			"W",
			897502,
			3995836
		],
		[
			"L",
			766759,
			3996891
		],
		null
	],
	"902409": [
		[
			"L",
			895172,
			3994754
		],
		null,
		null
	]
}