{
	"62948": [
		[
			"W",
			196791,
			918018
		],
		[
			"W",
			83880,
			926934
		],
		[
			"W",
			112704,
			928929
		]
	],
	"83880": [
		[
			"W",
			181069,
			908298
		],
		[
			"L",
			62948,
			926934
		],
		null
	],
	"112704": [
		[
			"W",
			168983,
			909297
		],
		[
			"W",
			156353,
			917670
		],
		[
			"L",
			62948,
			928929
		]
	],
	"156353": [
		[
			"W",
			163127,
			909912
		],
		[
			"L",
			112704,
			917670
		],
		null
	],
	"163127": [
		[
			"L",
			156353,
			909912
		],
		null,
		null
	],
	"168983": [
		[
			"L",
			112704,
			909297
		],
		null,
		null
	],
	"181069": [
		[
			"L",
			83880,
			908298
		],
		null,
		null
	],
	"196791": [
		[
			"L",
			62948,
			918018
		],
		null,
		null
	]
}