{
	"265337": "WWF..",
	"327221": "WBL..",
	"331205": "BF...",
	"334666": "WL...",
	"374747": "WL...",
	"402204": "WWBL.",
	"404666": "WWL..",
	"409394": "L....",
	"417285": "L....",
	"428473": "WWWWL",
	"431222": "L....",
	"432892": "F....",
	"449770": "L....",
	"460454": "L....",
	"466240": "L....",
	"482812": "BWL..",
	"483962": "L....",
	"489809": "L....",
	"490176": "L....",
	"493876": "F....",
	"495466": "WWWL.",
	"497130": "L....",
	"497973": "WL...",
	"498490": "L....",
	"498862": "L....",
	"499409": "WL...",
	"499610": "WL...",
	"499849": "WWWWW",
	"504980": "L....",
	"505334": "WL...",
	"506643": "WL...",
	"507520": "L...."
}