{
	"302550": [
		[
			"W",
			593707,
			3154764
		],
		[
			"L",
			595037,
			3156109
		],
		null
	],
	"576011": [
		[
			"W",
			605803,
			3153856
		],
		[
			"W",
			651409,
			3155107
		],
		[
			"W",
			595037,
			3156253
		]
	],
	"577586": [
		[
			"L",
			651409,
			3153487
		],
		null,
		null
	],
	"593707": [
		[
			"L",
			302550,
			3154764
		],
		null,
		null
	],
	"595037": [
		[
			"W",
			612794,
			3155068
		],
		[
			"W",
			302550,
			3156109
		],
		[
			"L",
			576011,
			3156253
		]
	],
	"605803": [
		[
			"L",
			576011,
			3153856
		],
		null,
		null
	],
	"612794": [
		[
			"L",
			595037,
			3155068
		],
		null,
		null
	],
	"651409": [
		[
			"W",
			577586,
			3153487
		],
		[
			"L",
			576011,
			3155107
		],
		null
	]
}