{
	"89604": [
		[
			"W",
			584401,
			3155868
		],
		[
			"W",
			180627,
			3157178
		],
		[
			"W",
			645357,
			3157950
		]
	],
	"129372": [
		[
			"L",
			648026,
			3156894
		],
		null,
		null
	],
	"180627": [
		[
			"W",
			473988,
			3156076
		],
		[
			"L",
			89604,
			3157178
		],
		null
	],
	"473988": [
		[
			"L",
			180627,
			3156076
		],
		null,
		null
	],
	"510150": [
		[
			"L",
			645357,
			3156810
		],
		null,
		null
	],
	"584401": [
		[
			"L",
			89604,
			3155868
		],
		null,
		null
	],
	"645357": [
		[
			"W",
			510150,
			3156810
		],
		[
			"W",
			648026,
			3157920
		],
		[
			"L",
			89604,
			3157950
		]
	],
	"648026": [
		[
			"W",
			129372,
			3156894
		],
		[
			"L",
			645357,
			3157920
		],
		null
	]
}