{
	"320835": [
		[
			"W",
			605803,
			3139768
		],
		[
			"L",
			537811,
			3142868
		],
		null
	],
	"360818": [
		[
			"W",
			562471,
			3140014
		],
		[
			"W",
			481893,
			3140339
		],
		[
			"L",
			537811,
			3143911
		]
	],
	"426070": [
		[
			"L",
			537811,
			3139363
		],
		null,
		null
	],
	"481893": [
		[
			"W",
			645507,
			3139090
		],
		[
			"L",
			360818,
			3140339
		],
		null
	],
	"537811": [
		[
			"W",
			426070,
			3139363
		],
		[
			"W",
			320835,
			3142868
		],
		[
			"W",
			360818,
			3143911
		]
	],
	"562471": [
		[
			"L",
			360818,
			3140014
		],
		null,
		null
	],
	"605803": [
		[
			"L",
			320835,
			3139768
		],
		null,
		null
	],
	"645507": [
		[
			"L",
			481893,
			3139090
		],
		null,
		null
	]
}