{
	"310812": [
		[
			"L",
			916870,
			4069700
		],
		null,
		null
	],
	"775542": [
		[
			"L",
			893086,
			4070164
		],
		null,
		null
	],
	"776972": [
		[
			"W",
			897979,
			4069398
		],
		[
			"W",
			916870,
			4070718
		],
		[
			"L",
			893086,
			4071366
		]
	],
	"883245": [
		[
			"W",
			933761,
			4070085
		],
		[
			"L",
			893086,
			4070398
		],
		null
	],
	"893086": [
		[
			"W",
			775542,
			4070164
		],
		[
			"W",
			883245,
			4070398
		],
		[
			"W",
			776972,
			4071366
		]
	],
	"897979": [
		[
			"L",
			776972,
			4069398
		],
		null,
		null
	],
	"916870": [
		[
			"W",
			310812,
			4069700
		],
		[
			"L",
			776972,
			4070718
		],
		null
	],
	"933761": [
		[
			"L",
			883245,
			4070085
		],
		null,
		null
	]
}