{
	"643202": [
		[
			"L",
			711587,
			3442688
		],
		[
			"W",
			647890,
			3443682
		],
		[
			"L",
			706261,
			3446607
		],
		[
			"W",
			723970,
			3451977
		]
	],
	"647890": [
		[
			"L",
			723970,
			3442512
		],
		[
			"L",
			643202,
			3443682
		],
		[
			"D",
			704997,
			3448200
		],
		[
			"L",
			682046,
			3449834
		]
	],
	"671467": [
		[
			"D",
			682046,
			3440906
		],
		[
			"W",
			704997,
			3444899
		],
		[
			"W",
			723970,
			3445824
		],
		[
			"L",
			706261,
			3448233
		]
	],
	"682046": [
		[
			"D",
			671467,
			3440906
		],
		[
			"D",
			706261,
			3444795
		],
		[
			"L",
			711587,
			3446432
		],
		[
			"W",
			647890,
			3449834
		]
	],
	"704997": [
		[
			"L",
			706261,
			3441563
		],
		[
			"L",
			671467,
			3444899
		],
		[
			"D",
			647890,
			3448200
		],
		[
			"W",
			711587,
			3449784
		]
	],
	"706261": [
		[
			"W",
			704997,
			3441563
		],
		[
			"D",
			682046,
			3444795
		],
		[
			"W",
			643202,
			3446607
		],
		[
			"W",
			671467,
			3448233
		]
	],
	"711587": [
		[
			"W",
			643202,
			3442688
		],
		[
			"L",
			723970,
			3444456
		],
		[
			"W",
			682046,
			3446432
		],
		[
			"L",
			704997,
			3449784
		]
	],
	"723970": [
		[
			"W",
			647890,
			3442512
		],
		[
			"W",
			711587,
			3444456
		],
		[
			"L",
			671467,
			3445824
		],
		[
			"L",
			643202,
			3451977
		]
	]
}