{
	"10944": [
		[
			"W",
			771211,
			3765823
		],
		[
			"W",
			778084,
			3767661
		],
		[
			"W",
			635777,
			3769940
		],
		[
			"L",
			826371,
			3770103
		]
	],
	"327245": [
		[
			"L",
			826371,
			3766612
		],
		null,
		null,
		null
	],
	"434339": [
		[
			"F",
			784776,
			null
		],
		null,
		null,
		null
	],
	"474287": [
		[
			"L",
			722621,
			3765593
		],
		null,
		null,
		null
	],
	"635777": [
		[
			"W",
			766576,
			3766987
		],
		[
			"W",
			722621,
			3768409
		],
		[
			"L",
			10944,
			3769940
		],
		null
	],
	"720927": [
		[
			"L",
			797875,
			3765832
		],
		null,
		null,
		null
	],
	"722621": [
		[
			"W",
			474287,
			3765593
		],
		[
			"L",
			635777,
			3768409
		],
		null,
		null
	],
	"766576": [
		[
			"L",
			635777,
			3766987
		],
		null,
		null,
		null
	],
	"771211": [
		[
			"L",
			10944,
			3765823
		],
		null,
		null,
		null
	],
	"773516": [
		[
			"W",
			814137,
			3766261
		],
		[
			"W",
			797875,
			3768270
		],
		[
			"L",
			826371,
			3769786
		],
		null
	],
	"778084": [
		[
			"W",
			782568,
			3765630
		],
		[
			"L",
			10944,
			3767661
		],
		null,
		null
	],
	"782568": [
		[
			"L",
			778084,
			3765630
		],
		null,
		null,
		null
	],
	"784776": [
		[
			"B",
			434339,
			null
		],
		[
			"F",
			826371,
			null
		],
		null,
		null
	],
	"797875": [
		[
			"W",
			720927,
			3765832
		],
		[
			"L",
			773516,
			3768270
		],
		null,
		null
	],
	"814137": [
		[
			"L",
			773516,
			3766261
		],
		null,
		null,
		null
	],
	"826371": [
		[
			"W",
			327245,
			3766612
		],
		[
			"B",
			784776,
			null
		],
		[
			"W",
			773516,
			3769786
		],
		[
			"W",
			10944,
			3770103
		]
	]
}