{
	"417848": [
		[
			"W",
			441628,
			2333119
		],
		[
			"W",
			489817,
			2333175
		],
		[
			"L",
			475732,
			2348189
		]
	],
	"441628": [
		[
			"L",
			417848,
			2333119
		],
		null,
		null
	],
	"466604": [
		[
			"W",
			486025,
			2333113
		],
		[
			"L",
			475732,
			2333245
		],
		null
	],
	"469051": [
		[
			"C",
			489817,
			2333107
		],
		null,
		null
	],
	"475732": [
		[
			"W",
			490298,
			2333149
		],
		[
			"W",
			466604,
			2333245
		],
		[
			"W",
			417848,
			2348189
		]
	],
	"486025": [
		[
			"L",
			466604,
			2333113
		],
		null,
		null
	],
	"489817": [
		[
			"W",
			469051,
			2333107
		],
		[
			"L",
			417848,
			2333175
		],
		null
	],
	"490298": [
		[
			"L",
			475732,
			2333149
		],
		null,
		null
	]
}