{
	"725239": "L....",
	"727685": "L....",
	"768970": "WL...",
	"785718": "L....",
	"810184": "WL...",
	"827969": "WL...",
	"835323": "WL...",
	"842049": "WWL..",
	"843752": "WL...",
	"847600": "WWWWL",
	"848789": "L....",
	"854405": "WWWL.",
	"855483": "L....",
	"859134": "WL...",
	"862316": "WL...",
	"862982": "L....",
	"874032": "WL...",
	"874524": "BWL..",
	"874822": "WWWL.",
	"878878": "WWWWW",
	"878892": "L....",
	"879637": "L....",
	"880131": "L....",
	"883737": "WWL..",
	"883944": "L....",
	"884151": "L....",
	"885424": "WWL..",
	"886423": "L....",
	"886625": "L....",
	"886688": "L....",
	"887802": "F....",
	"887820": "L...."
}