{
	"63775": [
		[
			"L",
			398813,
			2121774
		],
		[
			"L",
			427886,
			2121852
		],
		[
			"L",
			192890,
			2121964
		],
		[
			"L",
			173146,
			2122000
		]
	],
	"173146": [
		[
			"D",
			274518,
			2121780
		],
		[
			"W",
			192890,
			2121864
		],
		[
			"L",
			441146,
			2121962
		],
		[
			"W",
			63775,
			2122000
		]
	],
	"192890": [
		[
			"D",
			441146,
			2121776
		],
		[
			"L",
			173146,
			2121864
		],
		[
			"W",
			63775,
			2121964
		],
		[
			"D",
			427886,
			2122024
		]
	],
	"274518": [
		[
			"D",
			173146,
			2121780
		],
		[
			"W",
			441146,
			2121844
		],
		[
			"L",
			363754,
			2121946
		],
		[
			"W",
			398813,
			2122020
		]
	],
	"363754": [
		[
			"D",
			427886,
			2121782
		],
		[
			"L",
			398813,
			2121888
		],
		[
			"W",
			274518,
			2121946
		],
		[
			"W",
			441146,
			2122014
		]
	],
	"398813": [
		[
			"W",
			63775,
			2121774
		],
		[
			"W",
			363754,
			2121888
		],
		[
			"L",
			427886,
			2121974
		],
		[
			"L",
			274518,
			2122020
		]
	],
	"427886": [
		[
			"D",
			363754,
			2121782
		],
		[
			"W",
			63775,
			2121852
		],
		[
			"W",
			398813,
			2121974
		],
		[
			"D",
			192890,
			2122024
		]
	],
	"441146": [
		[
			"D",
			192890,
			2121776
		],
		[
			"L",
			274518,
			2121844
		],
		[
			"W",
			173146,
			2121962
		],
		[
			"L",
			363754,
			2122014
		]
	]
}