{
	"381363": [
		[
			"L",
			425135,
			2098486
		],
		null,
		null
	],
	"403563": [
		[
			"L",
			441671,
			2098561
		],
		null,
		null
	],
	"404817": [
		[
			"L",
			425885,
			2098513
		],
		null,
		null
	],
	"425135": [
		[
			"W",
			381363,
			2098486
		],
		[
			"L",
			439292,
			2098586
		],
		null
	],
	"425885": [
		[
			"W",
			404817,
			2098513
		],
		[
			"W",
			441671,
			2098683
		],
		[
			"L",
			439292,
			2104403
		]
	],
	"433684": [
		[
			"L",
			439292,
			2098476
		],
		null,
		null
	],
	"439292": [
		[
			"W",
			433684,
			2098476
		],
		[
			"W",
			425135,
			2098586
		],
		[
			"W",
			425885,
			2104403
		]
	],
	"441671": [
		[
			"W",
			403563,
			2098561
		],
		[
			"L",
			425885,
			2098683
		],
		null
	]
}