{
	"498801": [
		[
			"W",
			498806,
			2367493
		],
		[
			"W",
			498807,
			2367530
		],
		[
			"L",
			498803,
			2367641
		]
	],
	"498802": [
		[
			"L",
			498807,
			2367483
		],
		null,
		null
	],
	"498803": [
		[
			"W",
			498808,
			2367502
		],
		[
			"W",
			498805,
			2367566
		],
		[
			"W",
			498801,
			2367641
		]
	],
	"498804": [
		[
			"L",
			498805,
			2367516
		],
		null,
		null
	],
	"498805": [
		[
			"W",
			498804,
			2367516
		],
		[
			"C",
			498803,
			2367566
		],
		null
	],
	"498806": [
		[
			"L",
			498801,
			2367493
		],
		null,
		null
	],
	"498807": [
		[
			"W",
			498802,
			2367483
		],
		[
			"L",
			498801,
			2367530
		],
		null
	],
	"498808": [
		[
			"L",
			498803,
			2367502
		],
		null,
		null
	]
}