{
	"406145": [
		[
			"F",
			417164,
			null
		],
		null,
		null
	],
	"417164": [
		[
			"B",
			406145,
			null
		],
		[
			"L",
			481893,
			2413339
		],
		null
	],
	"454336": [
		[
			"L",
			503999,
			2413135
		],
		null,
		null
	],
	"480390": [
		[
			"L",
			492890,
			2413131
		],
		null,
		null
	],
	"481893": [
		[
			"W",
			492675,
			2413161
		],
		[
			"W",
			417164,
			2413339
		],
		[
			"W",
			492890,
			2419139
		]
	],
	"492675": [
		[
			"L",
			481893,
			2413161
		],
		null,
		null
	],
	"492890": [
		[
			"W",
			480390,
			2413131
		],
		[
			"W",
			503999,
			2413237
		],
		[
			"L",
			481893,
			2419139
		]
	],
	"503999": [
		[
			"W",
			454336,
			2413135
		],
		[
			"L",
			492890,
			2413237
		],
		null
	]
}