{
	"122094": [
		[
			"W",
			375213,
			2396030
		],
		[
			"W",
			321388,
			2396123
		],
		[
			"W",
			491715,
			2396248
		]
	],
	"321388": [
		[
			"W",
			499654,
			2395951
		],
		[
			"L",
			122094,
			2396123
		],
		null
	],
	"375213": [
		[
			"L",
			122094,
			2396030
		],
		null,
		null
	],
	"491715": [
		[
			"W",
			502645,
			2395947
		],
		[
			"W",
			498064,
			2396020
		],
		[
			"L",
			122094,
			2396248
		]
	],
	"496942": [
		[
			"L",
			498064,
			2395943
		],
		null,
		null
	],
	"498064": [
		[
			"W",
			496942,
			2395943
		],
		[
			"L",
			491715,
			2396020
		],
		null
	],
	"499654": [
		[
			"L",
			321388,
			2395951
		],
		null,
		null
	],
	"502645": [
		[
			"L",
			491715,
			2395947
		],
		null,
		null
	]
}