{
	"47750": [
		[
			"W",
			473983,
			2694343
		],
		[
			"W",
			556588,
			2694423
		],
		[
			"L",
			325438,
			2694673
		]
	],
	"98205": [
		[
			"L",
			325438,
			2694385
		],
		null,
		null
	],
	"118652": [
		[
			"W",
			416298,
			2694349
		],
		[
			"L",
			325438,
			2694519
		],
		null
	],
	"317810": [
		[
			"L",
			556588,
			2694354
		],
		null,
		null
	],
	"325438": [
		[
			"W",
			98205,
			2694385
		],
		[
			"W",
			118652,
			2694519
		],
		[
			"W",
			47750,
			2694673
		]
	],
	"416298": [
		[
			"L",
			118652,
			2694349
		],
		null,
		null
	],
	"473983": [
		[
			"L",
			47750,
			2694343
		],
		null,
		null
	],
	"556588": [
		[
			"W",
			317810,
			2694354
		],
		[
			"L",
			47750,
			2694423
		],
		null
	]
}