{
	"587738": [
		[
			"L",
			593279,
			2848751
		],
		null,
		null
	],
	"592818": [
		[
			"F",
			593331,
			null
		],
		null,
		null
	],
	"593067": [
		[
			"W",
			593496,
			2848515
		],
		[
			"L",
			593279,
			2854985
		],
		null
	],
	"593279": [
		[
			"W",
			587738,
			2848751
		],
		[
			"W",
			593067,
			2854985
		],
		[
			"W",
			593331,
			2862716
		]
	],
	"593331": [
		[
			"B",
			592818,
			null
		],
		[
			"B",
			593932,
			null
		],
		[
			"L",
			593279,
			2862716
		]
	],
	"593496": [
		[
			"L",
			593067,
			2848515
		],
		null,
		null
	],
	"593932": [
		[
			"W",
			593935,
			2846055
		],
		[
			"F",
			593331,
			null
		],
		null
	],
	"593935": [
		[
			"L",
			593932,
			2846055
		],
		null,
		null
	]
}