{
	"389813": [
		[
			"W",
			552277,
			2872687
		],
		[
			"L",
			568126,
			2872719
		],
		null
	],
	"432300": [
		[
			"W",
			467050,
			2872699
		],
		[
			"F",
			461590,
			null
		],
		null
	],
	"436610": [
		[
			"L",
			461590,
			2872693
		],
		null,
		null
	],
	"461590": [
		[
			"W",
			436610,
			2872693
		],
		[
			"B",
			432300,
			null
		],
		[
			"W",
			568126,
			2872845
		]
	],
	"467050": [
		[
			"L",
			432300,
			2872699
		],
		null,
		null
	],
	"508709": [
		[
			"L",
			568126,
			2872663
		],
		null,
		null
	],
	"552277": [
		[
			"L",
			389813,
			2872687
		],
		null,
		null
	],
	"568126": [
		[
			"W",
			508709,
			2872663
		],
		[
			"W",
			389813,
			2872719
		],
		[
			"L",
			461590,
			2872845
		]
	]
}