{
	"412776": [
		[
			"L",
			614255,
			2996631
		],
		null,
		null,
		null
	],
	"555422": [
		[
			"W",
			612660,
			2999129
		],
		[
			"W",
			614255,
			3004874
		],
		[
			"W",
			611752,
			3007615
		],
		[
			"W",
			612578,
			3008689
		]
	],
	"611673": [
		[
			"F",
			613887,
			null
		],
		null,
		null,
		null
	],
	"611752": [
		[
			"W",
			614992,
			2995572
		],
		[
			"W",
			611943,
			3005019
		],
		[
			"L",
			555422,
			3007615
		],
		null
	],
	"611943": [
		[
			"W",
			613387,
			2999639
		],
		[
			"L",
			611752,
			3005019
		],
		null,
		null
	],
	"611979": [
		[
			"L",
			614702,
			2994397
		],
		null,
		null,
		null
	],
	"612578": [
		[
			"W",
			612880,
			2992274
		],
		[
			"W",
			614702,
			2995085
		],
		[
			"W",
			613075,
			3005886
		],
		[
			"L",
			555422,
			3008689
		]
	],
	"612660": [
		[
			"L",
			555422,
			2999129
		],
		null,
		null,
		null
	],
	"612880": [
		[
			"L",
			612578,
			2992274
		],
		null,
		null,
		null
	],
	"612978": [
		[
			"L",
			613075,
			2992856
		],
		null,
		null,
		null
	],
	"613075": [
		[
			"W",
			612978,
			2992856
		],
		[
			"W",
			613887,
			3003623
		],
		[
			"L",
			612578,
			3005886
		],
		null
	],
	"613387": [
		[
			"L",
			611943,
			2999639
		],
		null,
		null,
		null
	],
	"613887": [
		[
			"B",
			611673,
			null
		],
		[
			"L",
			613075,
			3003623
		],
		null,
		null
	],
	"614255": [
		[
			"W",
			412776,
			2996631
		],
		[
			"L",
			555422,
			3004874
		],
		null,
		null
	],
	"614702": [
		[
			"W",
			611979,
			2994397
		],
		[
			"L",
			612578,
			2995085
		],
		null,
		null
	],
	"614992": [
		[
			"L",
			611752,
			2995572
		],
		null,
		null,
		null
	]
}