{
	"711475": [
		[
			"W",
			806048,
			3779713
		],
		[
			"W",
			832117,
			3780084
		],
		[
			"L",
			773584,
			3780456
		],
		null
	],
	"773584": [
		[
			"W",
			818785,
			3779251
		],
		[
			"W",
			830831,
			3779357
		],
		[
			"W",
			711475,
			3780456
		],
		[
			"L",
			801752,
			3787700
		]
	],
	"791667": [
		[
			"W",
			814118,
			3780598
		],
		[
			"L",
			801752,
			3782974
		],
		null,
		null
	],
	"798310": [
		[
			"W",
			832393,
			3779451
		],
		[
			"W",
			823835,
			3779760
		],
		[
			"L",
			801752,
			3784445
		],
		null
	],
	"801752": [
		[
			"W",
			833549,
			3780575
		],
		[
			"W",
			791667,
			3782974
		],
		[
			"W",
			798310,
			3784445
		],
		[
			"W",
			773584,
			3787700
		]
	],
	"806048": [
		[
			"L",
			711475,
			3779713
		],
		null,
		null,
		null
	],
	"814118": [
		[
			"L",
			791667,
			3780598
		],
		null,
		null,
		null
	],
	"818785": [
		[
			"L",
			773584,
			3779251
		],
		null,
		null,
		null
	],
	"819377": [
		[
			"L",
			823835,
			3779533
		],
		null,
		null,
		null
	],
	"823835": [
		[
			"W",
			819377,
			3779533
		],
		[
			"L",
			798310,
			3779760
		],
		null,
		null
	],
	"830831": [
		[
			"b",
			null,
			null
		],
		[
			"L",
			773584,
			3779357
		],
		null,
		null
	],
	"832100": [
		[
			"L",
			832117,
			3780008
		],
		null,
		null,
		null
	],
	"832117": [
		[
			"W",
			832100,
			3780008
		],
		[
			"L",
			711475,
			3780084
		],
		null,
		null
	],
	"832393": [
		[
			"L",
			798310,
			3779451
		],
		null,
		null,
		null
	],
	"833549": [
		[
			"L",
			801752,
			3780575
		],
		null,
		null,
		null
	]
}