{
	"374834": [
		[
			"W",
			592339,
			3786526
		],
		[
			"L",
			714164,
			3788692
		],
		null
	],
	"592339": [
		[
			"L",
			374834,
			3786526
		],
		null,
		null
	],
	"605803": [
		[
			"L",
			764076,
			3787408
		],
		null,
		null
	],
	"714164": [
		[
			"F",
			766975,
			null
		],
		[
			"W",
			374834,
			3788692
		],
		[
			"L",
			819471,
			3790206
		]
	],
	"764076": [
		[
			"W",
			605803,
			3787408
		],
		[
			"L",
			819471,
			3787895
		],
		null
	],
	"766975": [
		[
			"B",
			714164,
			null
		],
		[
			"Q",
			null,
			null
		],
		null
	],
	"819471": [
		[
			"W",
			825117,
			3786553
		],
		[
			"W",
			764076,
			3787895
		],
		[
			"W",
			714164,
			3790206
		]
	],
	"825117": [
		[
			"L",
			819471,
			3786553
		],
		null,
		null
	]
}