{
	"247552": [
		[
			"F",
			257585,
			null
		],
		null,
		null,
		null
	],
	"253921": [
		[
			"L",
			256892,
			1195718
		],
		null,
		null,
		null
	],
	"254984": [
		[
			"L",
			257833,
			1196102
		],
		null,
		null,
		null
	],
	"255020": [
		[
			"L",
			255992,
			1201166
		],
		null,
		null,
		null
	],
	"255992": [
		[
			"W",
			255020,
			1201166
		],
		[
			"W",
			257833,
			1202724
		],
		[
			"L",
			257585,
			1221493
		],
		null
	],
	"256892": [
		[
			"W",
			253921,
			1195718
		],
		[
			"L",
			258273,
			1206652
		],
		null,
		null
	],
	"257051": [
		[
			"W",
			257064,
			1198613
		],
		[
			"L",
			257585,
			1219733
		],
		null,
		null
	],
	"257064": [
		[
			"L",
			257051,
			1198613
		],
		null,
		null,
		null
	],
	"257165": [
		[
			"L",
			258273,
			1195470
		],
		null,
		null,
		null
	],
	"257482": [
		[
			"W",
			258146,
			1197316
		],
		[
			"L",
			257603,
			1205809
		],
		null,
		null
	],
	"257512": [
		[
			"L",
			257603,
			1195558
		],
		null,
		null,
		null
	],
	"257585": [
		[
			"B",
			247552,
			null
		],
		[
			"W",
			257051,
			1219733
		],
		[
			"W",
			255992,
			1221493
		],
		[
			"W",
			258273,
			1221653
		]
	],
	"257603": [
		[
			"W",
			257512,
			1195558
		],
		[
			"W",
			257482,
			1205809
		],
		[
			"L",
			258273,
			1208082
		],
		null
	],
	"257833": [
		[
			"W",
			254984,
			1196102
		],
		[
			"L",
			255992,
			1202724
		],
		null,
		null
	],
	"258146": [
		[
			"L",
			257482,
			1197316
		],
		null,
		null,
		null
	],
	"258273": [
		[
			"W",
			257165,
			1195470
		],
		[
			"W",
			256892,
			1206652
		],
		[
			"W",
			257603,
			1208082
		],
		[
			"L",
			257585,
			1221653
		]
	]
}