{
	"430991": [
		[
			"W",
			782924,
			3609981
		],
		[
			"L",
			747938,
			3610346
		],
		null,
		null,
		null
	],
	"469526": [
		[
			"W",
			783236,
			3610404
		],
		[
			"W",
			698259,
			3614480
		],
		[
			"W",
			783303,
			3615489
		],
		[
			"W",
			747938,
			3617206
		],
		[
			"L",
			670300,
			3618989
		]
	],
	"562538": [
		[
			"b",
			null,
			null
		],
		[
			"L",
			768107,
			3613261
		],
		null,
		null,
		null
	],
	"645266": [
		[
			"b",
			null,
			null
		],
		[
			"L",
			670300,
			3610692
		],
		null,
		null,
		null
	],
	"670300": [
		[
			"b",
			null,
			null
		],
		[
			"W",
			645266,
			3610692
		],
		[
			"B",
			768107,
			null
		],
		[
			"W",
			670486,
			3616886
		],
		[
			"W",
			469526,
			3618989
		]
	],
	"670486": [
		[
			"b",
			null,
			null
		],
		[
			"W",
			729734,
			3610048
		],
		[
			"W",
			782785,
			3612045
		],
		[
			"L",
			670300,
			3616886
		],
		null
	],
	"698259": [
		[
			"W",
			772473,
			3611068
		],
		[
			"L",
			469526,
			3614480
		],
		null,
		null,
		null
	],
	"702301": [
		[
			"b",
			null,
			null
		],
		[
			"L",
			782785,
			3609084
		],
		null,
		null,
		null
	],
	"718323": [
		[
			"L",
			747938,
			3610070
		],
		null,
		null,
		null,
		null
	],
	"729734": [
		[
			"b",
			null,
			null
		],
		[
			"L",
			670486,
			3610048
		],
		null,
		null,
		null
	],
	"747938": [
		[
			"W",
			718323,
			3610070
		],
		[
			"W",
			430991,
			3610346
		],
		[
			"W",
			756996,
			3615047
		],
		[
			"L",
			469526,
			3617206
		],
		null
	],
	"750804": [
		[
			"W",
			769605,
			3609257
		],
		[
			"L",
			783303,
			3610332
		],
		null,
		null,
		null
	],
	"756996": [
		[
			"W",
			764480,
			3611058
		],
		[
			"B",
			768580,
			null
		],
		[
			"L",
			747938,
			3615047
		],
		null,
		null
	],
	"764480": [
		[
			"L",
			756996,
			3611058
		],
		null,
		null,
		null,
		null
	],
	"768107": [
		[
			"b",
			null,
			null
		],
		[
			"W",
			562538,
			3613261
		],
		[
			"F",
			670300,
			null
		],
		null,
		null
	],
	"768580": [
		[
			"W",
			773134,
			3609777
		],
		[
			"F",
			756996,
			null
		],
		null,
		null,
		null
	],
	"769605": [
		[
			"L",
			750804,
			3609257
		],
		null,
		null,
		null,
		null
	],
	"772473": [
		[
			"L",
			698259,
			3611068
		],
		null,
		null,
		null,
		null
	],
	"773134": [
		[
			"L",
			768580,
			3609777
		],
		null,
		null,
		null,
		null
	],
	"780043": [
		[
			"L",
			783303,
			3609920
		],
		null,
		null,
		null,
		null
	],
	"782785": [
		[
			"b",
			null,
			null
		],
		[
			"W",
			702301,
			3609084
		],
		[
			"L",
			670486,
			3612045
		],
		null,
		null
	],
	"782924": [
		[
			"L",
			430991,
			3609981
		],
		null,
		null,
		null,
		null
	],
	"783236": [
		[
			"L",
			469526,
			3610404
		],
		null,
		null,
		null,
		null
	],
	"783303": [
		[
			"W",
			780043,
			3609920
		],
		[
			"W",
			750804,
			3610332
		],
		[
			"L",
			469526,
			3615489
		],
		null,
		null
	]
}