{
	"113624": [
		[
			"L",
			300480,
			1422257
		],
		null,
		null
	],
	"152823": [
		[
			"W",
			300639,
			1422233
		],
		[
			"L",
			300480,
			1422367
		],
		null
	],
	"288016": [
		[
			"L",
			296887,
			1422265
		],
		null,
		null
	],
	"296887": [
		[
			"W",
			288016,
			1422265
		],
		[
			"L",
			303780,
			1422403
		],
		null
	],
	"300480": [
		[
			"W",
			113624,
			1422257
		],
		[
			"W",
			152823,
			1422367
		],
		[
			"C",
			303780,
			1433134
		]
	],
	"300639": [
		[
			"L",
			152823,
			1422233
		],
		null,
		null
	],
	"301765": [
		[
			"L",
			303780,
			1422221
		],
		null,
		null
	],
	"303780": [
		[
			"W",
			301765,
			1422221
		],
		[
			"W",
			296887,
			1422403
		],
		[
			"W",
			300480,
			1433134
		]
	]
}