{
	"77558": [
		[
			"L",
			234260,
			1120507
		],
		null,
		null
	],
	"149971": [
		[
			"W",
			198628,
			1120525
		],
		[
			"W",
			234260,
			1120633
		],
		[
			"W",
			187292,
			1121948
		]
	],
	"162220": [
		[
			"W",
			231950,
			1120499
		],
		[
			"L",
			187292,
			1120613
		],
		null
	],
	"187292": [
		[
			"W",
			192335,
			1120448
		],
		[
			"W",
			162220,
			1120613
		],
		[
			"L",
			149971,
			1121948
		]
	],
	"192335": [
		[
			"C",
			187292,
			1120448
		],
		null,
		null
	],
	"198628": [
		[
			"L",
			149971,
			1120525
		],
		null,
		null
	],
	"231950": [
		[
			"L",
			162220,
			1120499
		],
		null,
		null
	],
	"234260": [
		[
			"W",
			77558,
			1120507
		],
		[
			"L",
			149971,
			1120633
		],
		null
	]
}