{
	"27805": [
		[
			"L",
			186640,
			1149758
		],
		null,
		null
	],
	"186640": [
		[
			"W",
			27805,
			1149758
		],
		[
			"W",
			226846,
			1149856
		],
		[
			"L",
			248042,
			1163975
		]
	],
	"222729": [
		[
			"L",
			226846,
			1149748
		],
		null,
		null
	],
	"226846": [
		[
			"W",
			222729,
			1149748
		],
		[
			"L",
			186640,
			1149856
		],
		null
	],
	"241777": [
		[
			"W",
			243392,
			1149744
		],
		[
			"L",
			248042,
			1149839
		],
		null
	],
	"243392": [
		[
			"L",
			241777,
			1149744
		],
		null,
		null
	],
	"245509": [
		[
			"L",
			248042,
			1149724
		],
		null,
		null
	],
	"248042": [
		[
			"W",
			245509,
			1149724
		],
		[
			"W",
			241777,
			1149839
		],
		[
			"W",
			186640,
			1163975
		]
	]
}