{
	"334608": [
		[
			"W",
			820509,
			3959933
		],
		[
			"L",
			645061,
			3961604
		],
		null,
		null
	],
	"456981": [
		[
			"L",
			807097,
			3959438
		],
		null,
		null,
		null
	],
	"582918": [
		[
			"L",
			667553,
			3959300
		],
		null,
		null,
		null
	],
	"645061": [
		[
			"W",
			737342,
			3959516
		],
		[
			"W",
			334608,
			3961604
		],
		[
			"W",
			667553,
			3963277
		],
		[
			"W",
			771319,
			3963773
		]
	],
	"667553": [
		[
			"W",
			582918,
			3959300
		],
		[
			"W",
			807097,
			3959784
		],
		[
			"L",
			645061,
			3963277
		],
		null
	],
	"737342": [
		[
			"L",
			645061,
			3959516
		],
		null,
		null,
		null
	],
	"745292": [
		[
			"b",
			null,
			null
		],
		[
			"W",
			890793,
			3959365
		],
		[
			"L",
			771319,
			3961744
		],
		null
	],
	"771319": [
		[
			"b",
			null,
			null
		],
		[
			"W",
			884672,
			3960220
		],
		[
			"W",
			745292,
			3961744
		],
		[
			"L",
			645061,
			3963773
		]
	],
	"807097": [
		[
			"W",
			456981,
			3959438
		],
		[
			"L",
			667553,
			3959784
		],
		null,
		null
	],
	"820509": [
		[
			"L",
			334608,
			3959933
		],
		null,
		null,
		null
	],
	"884672": [
		[
			"b",
			null,
			null
		],
		[
			"L",
			771319,
			3960220
		],
		null,
		null
	],
	"890793": [
		[
			"b",
			null,
			null
		],
		[
			"L",
			745292,
			3959365
		],
		null,
		null
	]
}