{
	"40119": [
		[
			"W",
			389803,
			1998659
		],
		[
			"L",
			366730,
			1998908
		],
		null
	],
	"169360": [
		[
			"W",
			359817,
			1998661
		],
		[
			"W",
			252269,
			1998900
		],
		[
			"L",
			366730,
			1999100
		]
	],
	"252269": [
		[
			"W",
			373727,
			1998623
		],
		[
			"L",
			169360,
			1998900
		],
		null
	],
	"302452": [
		[
			"L",
			366730,
			1998725
		],
		null,
		null
	],
	"359817": [
		[
			"L",
			169360,
			1998661
		],
		null,
		null
	],
	"366730": [
		[
			"W",
			302452,
			1998725
		],
		[
			"W",
			40119,
			1998908
		],
		[
			"W",
			169360,
			1999100
		]
	],
	"373727": [
		[
			"L",
			252269,
			1998623
		],
		null,
		null
	],
	"389803": [
		[
			"L",
			40119,
			1998659
		],
		null,
		null
	]
}