{
	"320835": [
		[
			"W",
			475246,
			2600039
		],
		[
			"W",
			400026,
			2600111
		],
		[
			"W",
			532411,
			2601243
		]
	],
	"400026": [
		[
			"W",
			540648,
			2599995
		],
		[
			"L",
			320835,
			2600111
		],
		null
	],
	"463403": [
		[
			"L",
			540371,
			2599989
		],
		null,
		null
	],
	"475246": [
		[
			"L",
			320835,
			2600039
		],
		null,
		null
	],
	"520777": [
		[
			"L",
			532411,
			2600015
		],
		null,
		null
	],
	"532411": [
		[
			"W",
			520777,
			2600015
		],
		[
			"W",
			540371,
			2600089
		],
		[
			"L",
			320835,
			2601243
		]
	],
	"540371": [
		[
			"W",
			463403,
			2599989
		],
		[
			"L",
			532411,
			2600089
		],
		null
	],
	"540648": [
		[
			"L",
			400026,
			2599995
		],
		null,
		null
	]
}