{
	"380435": [
		[
			"L",
			616261,
			3047983
		],
		null,
		null
	],
	"484492": [
		[
			"W",
			594240,
			3046617
		],
		[
			"L",
			616261,
			3050475
		],
		null
	],
	"578940": [
		[
			"F",
			622822,
			null
		],
		null,
		null
	],
	"594240": [
		[
			"L",
			484492,
			3046617
		],
		null,
		null
	],
	"616261": [
		[
			"W",
			380435,
			3047983
		],
		[
			"W",
			484492,
			3050475
		],
		[
			"W",
			623626,
			3052436
		]
	],
	"622822": [
		[
			"B",
			578940,
			null
		],
		[
			"L",
			623626,
			3049873
		],
		null
	],
	"622829": [
		[
			"L",
			623626,
			3047201
		],
		null,
		null
	],
	"623626": [
		[
			"W",
			622829,
			3047201
		],
		[
			"W",
			622822,
			3049873
		],
		[
			"L",
			616261,
			3052436
		]
	]
}